jinja2_registry/__init__.py
jinja2_registry/base.py
tests/__init__.py
tests/__main__.py
tests/test_basic.py
jinja2_registry-0.1.0.dist-info/top_level.txt
jinja2_registry-0.1.0.dist-info/METADATA
jinja2_registry-0.1.0.dist-info/DESCRIPTION.rst
jinja2_registry-0.1.0.dist-info/metadata.json
jinja2_registry-0.1.0.dist-info/WHEEL
jinja2_registry-0.1.0.dist-info/RECORD
