Metadata-Version: 2.0
Name: jinja2-registry
Version: 0.1.0
Summary: jinja2-registry
Home-page: https://3ptscience.com
Author: 3point Science
Author-email: info@3ptscience.com
License: MIT License
Download-URL: http://github.com/3ptscience/jinja2-registry
Keywords: templating
Platform: Windows
Platform: Linux
Platform: Solaris
Platform: Mac OS-X
Platform: Unix
Classifier: Development Status :: 4 - Beta
Classifier: Programming Language :: Python
Classifier: Programming Language :: Python :: 2.7
Classifier: Programming Language :: Python :: 3.3
Classifier: Programming Language :: Python :: 3.4
Classifier: Programming Language :: Python :: 3.5
Classifier: Operating System :: Microsoft :: Windows
Classifier: Operating System :: POSIX
Classifier: Operating System :: Unix
Classifier: Operating System :: MacOS
Classifier: Natural Language :: English
Requires-Dist: Jinja2 (>=2.6)
